ccds/__init__.py
ccds/__main__.py
ccds/monkey_patch.py
ccds/hook_utils/__init__.py
ccds/hook_utils/custom_config.py
ccds/hook_utils/dependencies.py
cookiecutter_data_science-2.2.0.dist-info/entry_points.txt
cookiecutter_data_science-2.2.0.dist-info/licenses/LICENSE
cookiecutter_data_science-2.2.0.dist-info/WHEEL
cookiecutter_data_science-2.2.0.dist-info/METADATA
cookiecutter_data_science-2.2.0.dist-info/RECORD
