Metadata-Version: 2.4
Name: cookiecutter-data-science
Version: 2.2.0
Summary: A logical, reasonably standardized but flexible project structure for doing and sharing data science work.
Author-email: DrivenData <info@drivendata.org>
Requires-Python: >=3.9
Classifier: Development Status :: 5 - Production/Stable
Classifier: Intended Audience :: Developers
Classifier: Intended Audience :: Science/Research
Classifier: License :: OSI Approved :: MIT License
Classifier: Programming Language :: Python :: 3
Classifier: Programming Language :: Python :: 3.9
Classifier: Programming Language :: Python :: 3.10
Classifier: Programming Language :: Python :: 3.11
Classifier: Programming Language :: Python :: 3.12
Classifier: Programming Language :: Python :: 3.13
Classifier: Topic :: Scientific/Engineering
Classifier: Topic :: Scientific/Engineering :: Artificial Intelligence
License-File: LICENSE
Requires-Dist: click
Requires-Dist: cookiecutter
Requires-Dist: tomlkit
Project-URL: Bug Tracker, https://github.com/drivendataorg/cookiecutter-data-science/issues
Project-URL: DrivenData, https://drivendata.co
Project-URL: Homepage, https://cookiecutter-data-science.drivendata.org/
Project-URL: Source Code, https://github.com/drivendataorg/cookiecutter-data-science/
